CHANGELOG.rst
COPYRIGHT.rst
LICENSE
MANIFEST.in
README
README.rst
README1.rst
setup.cfg
setup.py
doc/ImapLibrary.html
src/ImapLibrary/__init__.py
src/ImapLibrary/version.py
src/robotframework_imaplibrary.egg-info/PKG-INFO
src/robotframework_imaplibrary.egg-info/SOURCES.txt
src/robotframework_imaplibrary.egg-info/dependency_links.txt
src/robotframework_imaplibrary.egg-info/requires.txt
src/robotframework_imaplibrary.egg-info/top_level.txt