Metadata-Version: 1.1
Name: robotframework-imaplibrary
Version: 0.2.2
Summary: A IMAP email testing library for Robot Framework
Home-page: https://github.com/rickypc/robotframework-imaplibrary
Author: Richard Huang
Author-email: rickypc@users.noreply.github.com
License: Apache License, Version 2.0
Keywords: robot framework testing automation imap email mail softwaretesting
Platform: any
Classifier: Development Status :: 4 - Beta
Classifier: Intended Audience :: Developers
Classifier: Topic :: Software Development :: Testing
Classifier: License :: OSI Approved :: Apache Software License
Classifier: Programming Language :: Python :: 2.7
Classifier: Programming Language :: Python :: 3.5
